Sakesama_SpeechToText/__init__.py
Sakesama_SpeechToText/sakesama_STT.py
Sakesama4-0.1.dist-info/METADATA
Sakesama4-0.1.dist-info/WHEEL
Sakesama4-0.1.dist-info/top_level.txt
Sakesama4-0.1.dist-info/RECORD
