Metadata-Version: 2.1
Name: Sakesama4
Version: 0.1
Summary: This is a speech-to-text package created by Kaijakuri
Author: KaijaKuri
Author-email: example@gmail.com
Requires-Dist: selenium
Requires-Dist: webdriver-manager
